mockchain/__init__.py
mockchain/__main__.py
mockchain/conf.py
mockchain/processor.py
mockchain/webserver.py
mockchain/contracts/__init__.py
mockchain/contracts/submission.s.py
mockchain/contracts/genesis/__init__.py
mockchain/contracts/genesis/currency.s.py
tests/__init__.py
tests/test_processor.py
mockchain-0.1.dist-info/METADATA
mockchain-0.1.dist-info/WHEEL
mockchain-0.1.dist-info/top_level.txt
mockchain-0.1.dist-info/RECORD
