Metadata-Version: 2.1
Name: mockchain
Version: 0.1
Summary: A special Lamden blockchain instance that behaves like the regular network, but is self-hosted and flexible so that it can be used for development and testing.
Home-page: https://github.com/lamden/mockchain
Author: Lamden
Author-email: team@lamden.io
License: Creative Commons Non-Commercial
Platform: UNKNOWN
